{
  "nome": "Pessoa1",
  "senha": "123",
  "activeTab": "Magias",
  "spellDCConfig": {
    "selectedAttr": "for",
    "extraMod": 0,
    "lastKnownLevel": 0
  },
  "dtMagias": 19,
  "inventory": [
    {
      "id": 1766973012649,
      "name": "Escudo",
      "description": "<p>Pode ser de madeira ou metal.</p><ul style='list-style:none; padding-left:0; margin:0;'><li style='margin-bottom:4px;'><strong style='color:#9c27b0;'>◈ Preço:</strong> 10 po</li><li style='margin-bottom:4px;'><strong style='color:#9c27b0;'>◈ Peso:</strong> 3 kg</li></ul>",
      "expanded": true,
      "equip": true,
      "type": "Proteção",
      "isEquipable": true,
      "proficiency": "",
      "tipoItem": "Escudo",
      "minStrength": "0",
      "attunement": "Não",
      "minReqAttrs": [
        "Força"
      ],
      "disadvantageSkill": [],
      "advantageSkill": [],
      "defense": "2"
    },
    {
      "id": 1766806036855,
      "name": "Meia-Armadura",
      "description": "<p>Placas de metal moldadas cobrindo a maior parte do corpo.</p><ul style='list-style:none; padding-left:0; margin:0;'><li style='margin-bottom:4px;'><strong style='color:#9c27b0;'>◈ Preço:</strong> 750 po</li><li style='margin-bottom:4px;'><strong style='color:#9c27b0;'>◈ Peso:</strong> 20 kg</li></ul>",
      "expanded": false,
      "equip": false,
      "type": "Proteção",
      "isEquipable": true,
      "proficiency": "Media",
      "tipoItem": "Armadura",
      "minStrength": "0",
      "attunement": "Não",
      "minReqAttrs": [
        "Força"
      ],
      "disadvantageSkill": [],
      "advantageSkill": [],
      "defense": "123"
    },
    {
      "id": 1766806010141,
      "name": "Armadura de Batalha",
      "description": "<p>Armadura pesada robusta.</p><ul style='list-style:none; padding-left:0; margin:0;'><li style='margin-bottom:4px;'><strong style='color:#9c27b0;'>◈ Preço:</strong> 16 po</li><li style='margin-bottom:4px;'><strong style='color:#9c27b0;'>◈ Peso:</strong> 28 kg</li></ul>",
      "expanded": false,
      "equip": false,
      "type": "Proteção",
      "isEquipable": true,
      "proficiency": "Pesada",
      "tipoItem": "Armadura",
      "minStrength": "0",
      "attunement": "Não",
      "minReqAttrs": [
        "Força"
      ],
      "disadvantageSkill": [],
      "advantageSkill": [],
      "defense": "2"
    }
  ],
  "abilities": [
    {
      "id": 1767820786188,
      "title": "(Alma Profana, 3º nível) Magia do Pacto",
      "description": "<p>Você ganha conjuração de Bruxo.</p><ul style='list-style:none; padding-left:0; margin:0;'><li style='margin-bottom:4px;'><strong style='color:#9c27b0;'>◈ Recuperação:</strong> Espaços de magia recuperam em descanso curto ou longo.</li><li style='margin-bottom:4px;'><strong style='color:#9c27b0;'>◈ Atributo:</strong> Hemomancia (INT ou SAB).</li><li style='margin-bottom:4px;'><strong style='color:#9c27b0;'>◈ Foco:</strong> Arma com Rito ativo.</li></ul>",
      "expanded": false,
      "class": "Blood Hunter",
      "subclass": "Ordem da Alma Profana",
      "active": false
    }
  ],
  "description": {
    "anotacoes": "",
    "aparencia": "",
    "personalidade": "",
    "objetivo": "",
    "ideais": "",
    "vinculos": "",
    "fraquezas": "",
    "historia": ""
  },
  "sanidade": {
    "estresse": 4,
    "vazio": 144
  },
  "spells": [
    {
      "id": 1766798046234,
      "name": "Sono",
      "levelNumber": 1,
      "damage": "-",
      "expanded": false,
      "active": true,
      "components": {
        "V": true,
        "S": true,
        "M": true
      },
      "material": "Areia, pétalas ou grilo",
      "attrs": {
        "execucao": "1 ação",
        "alcance": "36m",
        "area": "Esfera 6m",
        "alvo": "Vários",
        "duracao": "1 min",
        "resistencia": "-"
      },
      "school": "Encantamento",
      "spellClass": "Blood Hunter",
      "description": "<p>Role <strong>5d8</strong>. Adormece criaturas na área em ordem ascendente de seus PV atuais.</p><p><strong>Níveis Superiores:</strong> +2d8 por nível de slot.</p>"
    },
    {
      "id": 1766798008908,
      "name": "Sono",
      "levelNumber": 1,
      "school": "Encantamento",
      "spellClass": "Mago",
      "damage": "-",
      "components": {
        "V": true,
        "S": true,
        "M": true
      },
      "material": "Areia, pétalas ou grilo",
      "attrs": {
        "execucao": "1 ação",
        "alcance": "36m",
        "area": "Esfera 6m",
        "alvo": "Vários",
        "duracao": "1 min",
        "resistencia": "-"
      },
      "description": "<p>Role <strong>5d8</strong>. Adormece criaturas na área em ordem ascendente de seus PV atuais.</p><p><strong>Níveis Superiores:</strong> +2d8 por nível de slot.</p>",
      "expanded": false,
      "active": false
    }
  ],
  "abilityCatalog": [],
  "spellCatalog": [],
  "pericias": {
    "Atletismo": {
      "atributo": "FOR",
      "treinado": false,
      "outros": 0
    },
    "Acrobacia": {
      "atributo": "DEX",
      "treinado": false,
      "outros": 46
    },
    "Furtividade": {
      "atributo": "DEX",
      "treinado": false,
      "outros": 0
    },
    "Prestidigitação": {
      "atributo": "DEX",
      "treinado": false,
      "outros": 0
    },
    "Arcanismo": {
      "atributo": "INT",
      "treinado": false,
      "outros": 0
    },
    "História": {
      "atributo": "INT",
      "treinado": false,
      "outros": 5
    },
    "Investigação": {
      "atributo": "INT",
      "treinado": false,
      "outros": 3
    },
    "Natureza": {
      "atributo": "INT",
      "treinado": false,
      "outros": 0
    },
    "Religião": {
      "atributo": "INT",
      "treinado": false,
      "outros": 0
    },
    "Intuição": {
      "atributo": "SAB",
      "treinado": false,
      "outros": 0
    },
    "Lidar com animais": {
      "atributo": "SAB",
      "treinado": true,
      "outros": 3
    },
    "Medicina": {
      "atributo": "SAB",
      "treinado": false,
      "outros": 0
    },
    "Percepção": {
      "atributo": "SAB",
      "treinado": false,
      "outros": 0
    },
    "Sobrevivência": {
      "atributo": "SAB",
      "treinado": false,
      "outros": 0
    },
    "Atuação": {
      "atributo": "CAR",
      "treinado": false,
      "outros": 0
    },
    "Enganação": {
      "atributo": "CAR",
      "treinado": false,
      "outros": 0
    },
    "Intimidação": {
      "atributo": "CAR",
      "treinado": false,
      "outros": 0
    },
    "Persuasão": {
      "atributo": "CAR",
      "treinado": false,
      "outros": 0
    },
    "Salvaguarda (Força)": {
      "atributo": "FOR",
      "treinado": false,
      "outros": 0
    },
    "Salvaguarda (Destreza)": {
      "atributo": "DEX",
      "treinado": false,
      "outros": 0
    },
    "Salvaguarda (Constituição)": {
      "atributo": "CON",
      "treinado": false,
      "outros": 0
    },
    "Salvaguarda (Inteligência)": {
      "atributo": "INT",
      "treinado": false,
      "outros": 0
    },
    "Salvaguarda (Sabedoria)": {
      "atributo": "SAB",
      "treinado": false,
      "outros": 343
    },
    "Salvaguarda (Carisma)": {
      "atributo": "CAR",
      "treinado": false,
      "outros": 0
    }
  },
  "atributos": {
    "n1": 32,
    "n2": 20,
    "n3": 10,
    "n4": 10,
    "n5": 10,
    "n6": 20
  },
  "niveisClasses": {
    "artifice": 0,
    "barbaro": 0,
    "bardo": 0,
    "blood hunter": 20,
    "bruxo": 0,
    "clerigo": 0,
    "monge": 0,
    "druida": 0,
    "feiticeiro": 0,
    "guerreiro": 0,
    "ladino": 0,
    "mago": 0,
    "paladino": 0,
    "patrulheiro": 0
  },
  "xp": "2345667",
  "inspiracao": 4,
  "vidaDadosSalvos": {},
  "marco": 2,
  "vidaAtual": 105,
  "vidaTempAtual": 71,
  "danoNecroAtual": 60,
  "metros": 364.5,
  "iniciativaBonus": 87,
  "acOutros": 0,
  "resistencias": "23",
  "imunidades": "234",
  "fraquezas": "234",
  "proficiencias": "q3r",
  "minimizedPreparedSpells": false,
  "minimizedPreparedAbilities": false,
  "fraquezasList": [
    "Ácido",
    "Contundente",
    "Cortante",
    "Perfurante",
    "Fogo",
    "Elétrico",
    "Veneno",
    "Trovão",
    "Radiante",
    "Necrótico"
  ],
  "resistenciasList": [
    "Contundente",
    "Perfurante",
    "Frio"
  ],
  "imunidadesList": [],
  "proficienciasList": [
    "Armaduras médias",
    "Armaduras leves",
    "Armaduras pesadas"
  ],
  "idiomasList": [
    "Gíria de Ladrões",
    "Druídico",
    "Silvestre",
    "Primordial",
    "Infernal",
    "Dialeto Subterrâneo",
    "Dracônico"
  ],
  "spellSlots": {
    "1": {
      "used": 0,
      "status": [
        false,
        false,
        false,
        false
      ]
    },
    "2": {
      "used": 0,
      "status": [
        false,
        false,
        false
      ]
    },
    "3": {
      "used": 0,
      "status": [
        false,
        false,
        false
      ]
    },
    "4": {
      "used": 0,
      "status": [
        false,
        false,
        false
      ]
    },
    "5": {
      "used": 0,
      "status": [
        false,
        false,
        false
      ]
    },
    "6": {
      "used": 0,
      "status": [
        false,
        false
      ]
    },
    "7": {
      "used": 0,
      "status": [
        false,
        false
      ]
    },
    "8": {
      "used": 0,
      "status": [
        false
      ]
    },
    "9": {
      "used": 0,
      "status": [
        false
      ]
    },
    "pact": {
      "used": 0,
      "status": [
        false,
        false,
        false,
        false
      ]
    },
    "ki": {
      "used": 0,
      "status": [
        false,
        false,
        false,
        false,
        false,
        false,
        false,
        false,
        false,
        false,
        false,
        false,
        false,
        false,
        false,
        false,
        false,
        false,
        false,
        false
      ]
    },
    "furia": {
      "used": 0,
      "status": [
        false,
        false,
        false,
        false,
        false,
        false,
        false,
        false,
        false,
        false,
        false,
        false,
        false,
        false,
        false,
        false,
        false,
        false,
        false,
        false,
        false,
        false,
        false,
        false,
        false,
        false,
        false,
        false,
        false,
        false,
        false,
        false,
        false,
        false,
        false,
        false,
        false,
        false,
        false,
        false,
        false,
        false,
        false,
        false,
        false,
        false,
        false,
        false,
        false,
        false,
        false,
        false,
        false,
        false,
        false,
        false,
        false,
        false,
        false,
        false,
        false,
        false,
        false,
        false,
        false,
        false,
        false,
        false,
        false,
        false,
        false,
        false,
        false,
        false,
        false,
        false,
        false,
        false,
        false,
        false,
        false,
        false,
        false,
        false,
        false,
        false,
        false,
        false,
        false,
        false,
        false,
        false,
        false,
        false,
        false,
        false,
        false,
        false,
        false
      ]
    },
    "sorcery": {
      "used": 0,
      "status": [
        false,
        false,
        false,
        false,
        true,
        false,
        true,
        false,
        true,
        false,
        true,
        false,
        false,
        false,
        false,
        false,
        false,
        true,
        false,
        false
      ]
    },
    "mutagen": {
      "used": 0,
      "status": [
        false,
        false,
        false
      ]
    },
    "blood_curse": {
      "status": [
        false,
        false,
        false,
        false
      ]
    },
    "infusions": {
      "status": [
        false,
        false,
        false,
        false,
        false,
        false
      ]
    }
  },
  "isSlotsCollapsed": false,
  "collapsedSections": {
    "class-Blood Hunter": false
  }
}